NUcmd/__init__.py
NUcmd/converter.py
nucmd-0.1.dist-info/licenses/LICENSE.txt
nucmd-0.1.dist-info/METADATA
nucmd-0.1.dist-info/WHEEL
nucmd-0.1.dist-info/entry_points.txt
nucmd-0.1.dist-info/top_level.txt
nucmd-0.1.dist-info/RECORD
